token_copilot/__init__.py
token_copilot/context.py
token_copilot/decorators.py
token_copilot/presets.py
token_copilot/adaptive/__init__.py
token_copilot/adaptive/context.py
token_copilot/adaptive/decorators.py
token_copilot/adaptive/operations.py
token_copilot/adaptive/tiers.py
token_copilot/analytics/__init__.py
token_copilot/analytics/alerts.py
token_copilot/analytics/anomaly_detector.py
token_copilot/analytics/efficiency_scorer.py
token_copilot/analytics/waste_analyzer.py
token_copilot/core/__init__.py
token_copilot/core/copilot.py
token_copilot/core/plugin.py
token_copilot/forecasting/__init__.py
token_copilot/forecasting/alert_manager.py
token_copilot/forecasting/predictor.py
token_copilot/langchain/__init__.py
token_copilot/langchain/callbacks.py
token_copilot/llamaindex/__init__.py
token_copilot/llamaindex/callbacks.py
token_copilot/plugins/__init__.py
token_copilot/plugins/adaptive.py
token_copilot/plugins/analytics.py
token_copilot/plugins/forecasting.py
token_copilot/plugins/persistence.py
token_copilot/plugins/routing.py
token_copilot/plugins/streaming.py
token_copilot/queuing/__init__.py
token_copilot/queuing/queue_manager.py
token_copilot/routing/__init__.py
token_copilot/routing/router.py
token_copilot/streaming/__init__.py
token_copilot/streaming/base.py
token_copilot/streaming/kafka_stream.py
token_copilot/streaming/logstash.py
token_copilot/streaming/opentelemetry.py
token_copilot/streaming/syslog.py
token_copilot/streaming/webhook.py
token_copilot/tracking/__init__.py
token_copilot/tracking/budget.py
token_copilot/tracking/tracker.py
token_copilot/utils/__init__.py
token_copilot/utils/exceptions.py
token_copilot/utils/pricing.py
token_copilot-1.0.2.dist-info/licenses/LICENSE
token_copilot-1.0.2.dist-info/METADATA
token_copilot-1.0.2.dist-info/WHEEL
token_copilot-1.0.2.dist-info/top_level.txt
token_copilot-1.0.2.dist-info/RECORD
