Metadata-Version: 2.4
Name: token-copilot
Version: 1.0.2
Summary: Your AI copilot for LLM costs - Modern, plugin-based cost tracking for LangChain, LangGraph, and LlamaIndex with 5 usage patterns
Author-email: Sai Kumar Yava <saikumar.geek@gmail.com>
License: MIT
Project-URL: Homepage, https://github.com/scionoftech/token-copilot
Project-URL: Documentation, https://github.com/scionoftech/token-copilot#readme
Project-URL: Repository, https://github.com/scionoftech/token-copilot
Project-URL: Issues, https://github.com/scionoftech/token-copilot/issues
Keywords: llm,langchain,langgraph,llamaindex,cost-tracking,budget,ai,openai,anthropic,multi-tenant,cost-optimization,analytics,monitoring,observability,token-tracking,budget-enforcement
Classifier: Development Status :: 5 - Production/Stable
Classifier: Intended Audience :: Developers
Classifier: License :: OSI Approved :: MIT License
Classifier: Programming Language :: Python :: 3
Classifier: Programming Language :: Python :: 3.8
Classifier: Programming Language :: Python :: 3.9
Classifier: Programming Language :: Python :: 3.10
Classifier: Programming Language :: Python :: 3.11
Classifier: Programming Language :: Python :: 3.12
Classifier: Topic :: Software Development :: Libraries :: Python Modules
Classifier: Topic :: Scientific/Engineering :: Artificial Intelligence
Classifier: Typing :: Typed
Requires-Python: >=3.8
License-File: LICENSE
Requires-Dist: langchain-core>=0.1.0
Provides-Extra: dev
Requires-Dist: pytest>=7.4.0; extra == "dev"
Requires-Dist: pytest-cov>=4.1.0; extra == "dev"
Requires-Dist: pytest-asyncio>=0.21.0; extra == "dev"
Requires-Dist: black>=23.0.0; extra == "dev"
Requires-Dist: isort>=5.12.0; extra == "dev"
Requires-Dist: flake8>=6.0.0; extra == "dev"
Requires-Dist: mypy>=1.5.0; extra == "dev"
Requires-Dist: pre-commit>=3.3.0; extra == "dev"
Provides-Extra: docs
Requires-Dist: sphinx>=7.0.0; extra == "docs"
Requires-Dist: sphinx-rtd-theme>=1.3.0; extra == "docs"
Requires-Dist: myst-parser>=2.0.0; extra == "docs"
Provides-Extra: analytics
Requires-Dist: pandas>=2.0.0; extra == "analytics"
Requires-Dist: matplotlib>=3.7.0; extra == "analytics"
Requires-Dist: numpy>=1.24.0; extra == "analytics"
Provides-Extra: streaming
Requires-Dist: requests>=2.28.0; extra == "streaming"
Requires-Dist: kafka-python>=2.0.2; extra == "streaming"
Requires-Dist: opentelemetry-api>=1.20.0; extra == "streaming"
Requires-Dist: opentelemetry-sdk>=1.20.0; extra == "streaming"
Requires-Dist: opentelemetry-exporter-otlp>=1.20.0; extra == "streaming"
Provides-Extra: langchain
Requires-Dist: langchain-openai>=0.1.0; extra == "langchain"
Provides-Extra: llamaindex
Requires-Dist: llama-index-core>=0.10.0; extra == "llamaindex"
Requires-Dist: llama-index-llms-openai>=0.1.0; extra == "llamaindex"
Provides-Extra: langgraph
Requires-Dist: langgraph>=0.2.0; extra == "langgraph"
Provides-Extra: examples
Requires-Dist: langchain-openai>=0.1.0; extra == "examples"
Requires-Dist: llama-index-core>=0.10.0; extra == "examples"
Requires-Dist: llama-index-llms-openai>=0.1.0; extra == "examples"
Requires-Dist: langgraph>=0.2.0; extra == "examples"
Provides-Extra: all
Requires-Dist: token-copilot[analytics,dev,docs,langchain,langgraph,llamaindex,streaming]; extra == "all"
Dynamic: license-file
